{"Year":["2013","2014","2015","2016","2017","2018","2019","2013","2014","2015","2016","2017","2018","2019","2013","2014","2015","2016","2017","2018","2019","2013","2014","2015","2016","2017","2018","2019","2013","2014","2015","2016","2017","2018","2019","2013","2014","2015","2016","2017","2018","2019"],"Observation status":["Normal value","Normal value","Normal value","Normal value","Normal value","Normal value","Normal value","Normal value","Normal value","Normal value","Normal value","Normal value","Normal value","Normal value","Normal value","Normal value","Normal value","Normal value","Normal value","Normal value","Normal value","Normal value","Normal value","Normal value","Normal value","Normal value","Normal value","Normal value","Normal value","Normal value","Normal value","Normal value","Normal value","Normal value","Normal value","Normal value","Normal value","Normal value","Normal value","Normal value","Normal value","Normal value"],"Unit multiplier":["Units","Units","Units","Units","Units","Units","Units","Units","Units","Units","Units","Units","Units","Units","Units","Units","Units","Units","Units","Units","Units","Units","Units","Units","Units","Units","Units","Units","Units","Units","Units","Units","Units","Units","Units","Units","Units","Units","Units","Units","Units","Units"],"Nature of data points":["Country Data","Country Data","Country Data","Country Data","Country Data","Country Data","Country Data","Country Data","Country Data","Country Data","Country Data","Country Data","Country Data","Country Data","Country Data","Country Data","Country Data","Country Data","Country Data","Country Data","Country Data","Country Data","Country Data","Country Data","Country Data","Country Data","Country Data","Country Data","Country Data","Country Data","Country Data","Country Data","Country Data","Country Data","Country Data","Country Data","Country Data","Country Data","Country Data","Country Data","Country Data","Country Data"],"Frequency of observation":["Annual","Annual","Annual","Annual","Annual","Annual","Annual","Annual","Annual","Annual","Annual","Annual","Annual","Annual","Annual","Annual","Annual","Annual","Annual","Annual","Annual","Annual","Annual","Annual","Annual","Annual","Annual","Annual","Annual","Annual","Annual","Annual","Annual","Annual","Annual","Annual","Annual","Annual","Annual","Annual","Annual","Annual"],"Reporting type":["National","National","National","National","National","National","National","National","National","National","National","National","National","National","National","National","National","National","National","National","National","National","National","National","National","National","National","National","National","National","National","National","National","National","National","National","National","National","National","National","National","National"],"SERIES":["Share of Red Book species from all species of corresponding class","Share of Red Book species from all species of corresponding class","Share of Red Book species from all species of corresponding class","Share of Red Book species from all species of corresponding class","Share of Red Book species from all species of corresponding class","Share of Red Book species from all species of corresponding class","Share of Red Book species from all species of corresponding class","Share of Red Book species from all species of corresponding class","Share of Red Book species from all species of corresponding class","Share of Red Book species from all species of corresponding class","Share of Red Book species from all species of corresponding class","Share of Red Book species from all species of corresponding class","Share of Red Book species from all species of corresponding class","Share of Red Book species from all species of corresponding class","Share of Red Book species from all species of corresponding class","Share of Red Book species from all species of corresponding class","Share of Red Book species from all species of corresponding class","Share of Red Book species from all species of corresponding class","Share of Red Book species from all species of corresponding class","Share of Red Book species from all species of corresponding class","Share of Red Book species from all species of corresponding class","Share of Red Book species from all species of corresponding class","Share of Red Book species from all species of corresponding class","Share of Red Book species from all species of corresponding class","Share of Red Book species from all species of corresponding class","Share of Red Book species from all species of corresponding class","Share of Red Book species from all species of corresponding class","Share of Red Book species from all species of corresponding class","Share of Red Book species from all species of corresponding class","Share of Red Book species from all species of corresponding class","Share of Red Book species from all species of corresponding class","Share of Red Book species from all species of corresponding class","Share of Red Book species from all species of corresponding class","Share of Red Book species from all species of corresponding class","Share of Red Book species from all species of corresponding class","Share of Red Book species from all species of corresponding class","Share of Red Book species from all species of corresponding class","Share of Red Book species from all species of corresponding class","Share of Red Book species from all species of corresponding class","Share of Red Book species from all species of corresponding class","Share of Red Book species from all species of corresponding class","Share of Red Book species from all species of corresponding class"],"Reference area":["Kyrgyzstan","Kyrgyzstan","Kyrgyzstan","Kyrgyzstan","Kyrgyzstan","Kyrgyzstan","Kyrgyzstan","Kyrgyzstan","Kyrgyzstan","Kyrgyzstan","Kyrgyzstan","Kyrgyzstan","Kyrgyzstan","Kyrgyzstan","Kyrgyzstan","Kyrgyzstan","Kyrgyzstan","Kyrgyzstan","Kyrgyzstan","Kyrgyzstan","Kyrgyzstan","Kyrgyzstan","Kyrgyzstan","Kyrgyzstan","Kyrgyzstan","Kyrgyzstan","Kyrgyzstan","Kyrgyzstan","Kyrgyzstan","Kyrgyzstan","Kyrgyzstan","Kyrgyzstan","Kyrgyzstan","Kyrgyzstan","Kyrgyzstan","Kyrgyzstan","Kyrgyzstan","Kyrgyzstan","Kyrgyzstan","Kyrgyzstan","Kyrgyzstan","Kyrgyzstan"],"COMPOSITE_BREAKDOWN":["Species: Plants and mushrooms","Species: Plants and mushrooms","Species: Plants and mushrooms","Species: Plants and mushrooms","Species: Plants and mushrooms","Species: Plants and mushrooms","Species: Plants and mushrooms","Species: Mammals","Species: Mammals","Species: Mammals","Species: Mammals","Species: Mammals","Species: Mammals","Species: Mammals","Species: Birds","Species: Birds","Species: Birds","Species: Birds","Species: Birds","Species: Birds","Species: Birds","Species: Insects","Species: Insects","Species: Insects","Species: Insects","Species: Insects","Species: Insects","Species: Insects","Species: Amphibians and Reptiles","Species: Amphibians and Reptiles","Species: Amphibians and Reptiles","Species: Amphibians and Reptiles","Species: Amphibians and Reptiles","Species: Amphibians and Reptiles","Species: Amphibians and Reptiles","Species: Fish","Species: Fish","Species: Fish","Species: Fish","Species: Fish","Species: Fish","Species: Fish"],"UNIT_MEASURE":["Percent","Percent","Percent","Percent","Percent","Percent","Percent","Percent","Percent","Percent","Percent","Percent","Percent","Percent","Percent","Percent","Percent","Percent","Percent","Percent","Percent","Percent","Percent","Percent","Percent","Percent","Percent","Percent","Percent","Percent","Percent","Percent","Percent","Percent","Percent","Percent","Percent","Percent","Percent","Percent","Percent","Percent"],"Value":[1.07,1.07,1.07,1.07,1.07,1.07,1.07,25.3,25.3,25.3,25.3,25.3,25.3,25.27,14.0,14.0,14.0,14.0,14.0,14.0,14.0,0.12,0.12,0.12,0.12,0.12,0.12,0.12,21.7,21.7,21.7,21.7,21.7,21.7,21.74,9.5,9.5,9.5,9.5,9.5,9.5,9.46]}